jaya_algorithm/__init__.py
jaya_algorithm/core.py
tests/__init__.py
tests/test_core.py
jaya_optimizer-0.1.2.dist-info/LICENSE
jaya_optimizer-0.1.2.dist-info/METADATA
jaya_optimizer-0.1.2.dist-info/WHEEL
jaya_optimizer-0.1.2.dist-info/top_level.txt
jaya_optimizer-0.1.2.dist-info/RECORD
