Metadata-Version: 2.1
Name: jaya-optimizer
Version: 0.1.2
Summary: A Python library implementing the Jaya Optimization Algorithm.
Home-page: https://github.com/Ravikumar-Shah-2804/jaya-optimizer.git
Author: Ravikumar Shah
Author-email: ravikumar.shah.2804@gmail.com
Classifier: Programming Language :: Python :: 3
Classifier: License :: OSI Approved :: MIT License
Classifier: Operating System :: OS Independent
Requires-Python: >=3.6
License-File: LICENSE
Requires-Dist: numpy
